rubiapi/__init__.py
rubiapi/api.py
rubiapi/button.py
rubiapi/config.py
rubiapi/context.py
rubiapi/decorators.py
rubiapi/exceptions.py
rubiapi/jobs.py
rubiapi/keyboards.py
rubiapi/keypad.py
rubiapi/logger.py
rubiapi/rubino.py
rubiapi/utils.py
rubiapi/adaptorrubiapi/__init__.py
rubiapi/adaptorrubiapi/enums.py
rubiapi/adaptorrubiapi/exceptions.py
rubiapi/adaptorrubiapi/client/__init__.py
rubiapi/adaptorrubiapi/client/client.py
rubiapi/adaptorrubiapi/crypto/__init__.py
rubiapi/adaptorrubiapi/crypto/crypto.py
rubiapi/adaptorrubiapi/methods/__init__.py
rubiapi/adaptorrubiapi/methods/methods.py
rubiapi/adaptorrubiapi/network/__init__.py
rubiapi/adaptorrubiapi/network/helper.py
rubiapi/adaptorrubiapi/network/network.py
rubiapi/adaptorrubiapi/network/socket.py
rubiapi/adaptorrubiapi/sessions/__init__.py
rubiapi/adaptorrubiapi/sessions/sessions.py
rubiapi/adaptorrubiapi/types/__init__.py
rubiapi/adaptorrubiapi/types/socket/__init__.py
rubiapi/adaptorrubiapi/types/socket/message.py
rubiapi/adaptorrubiapi/utils/__init__.py
rubiapi/adaptorrubiapi/utils/configs.py
rubiapi/adaptorrubiapi/utils/utils.py
rubiapi-1.3.0.dist-info/METADATA
rubiapi-1.3.0.dist-info/WHEEL
rubiapi-1.3.0.dist-info/top_level.txt
rubiapi-1.3.0.dist-info/RECORD
