Metadata-Version: 2.4
Name: RubiApi
Version: 1.3.0
Summary: A Python library for interacting with Rubika Bot API.
Home-page: https://github.com/iTs-GoJo/RubiApi
Download-URL: https://github.com/iTs-GoJo/RubiApi/archive/refs/tags/v0.1.0.tar.gz
Author: ali jafari
Author-email: thealiapi@gmail.com
Maintainer: ali jafari
Maintainer-email: thealiapi@gmail.com
Classifier: Programming Language :: Python :: 3
Classifier: License :: OSI Approved :: MIT License
Classifier: Operating System :: OS Independent
Classifier: Topic :: Communications :: Chat
Classifier: Topic :: Software Development :: Libraries
Requires-Python: >=3.6
Requires-Dist: requests
Dynamic: author
Dynamic: author-email
Dynamic: classifier
Dynamic: description
Dynamic: description-content-type
Dynamic: download-url
Dynamic: home-page
Dynamic: maintainer
Dynamic: maintainer-email
Dynamic: requires-dist
Dynamic: requires-python
Dynamic: summary
